llama_index/readers/pandas_ai/__init__.py
llama_index/readers/pandas_ai/base.py
llama_index_readers_pandas_ai-0.5.1.dist-info/METADATA
llama_index_readers_pandas_ai-0.5.1.dist-info/WHEEL
llama_index_readers_pandas_ai-0.5.1.dist-info/licenses/LICENSE
llama_index_readers_pandas_ai-0.5.1.dist-info/RECORD
