Metadata-Version: 2.4
Name: llama-index-readers-pandas-ai
Version: 0.5.1
Summary: llama-index readers pandas_ai integration
Author-email: Your Name <you@example.com>
Maintainer: jerryjliu
License-Expression: MIT
License-File: LICENSE
Keywords: ai,pandas
Requires-Python: <4.0,>=3.9
Requires-Dist: llama-index-core<0.15,>=0.13.0
Requires-Dist: llama-index-readers-file<0.6,>=0.5.0
Requires-Dist: numpy<2.0
Requires-Dist: pandas
Requires-Dist: pandasai>=2.2.12
